orientationpy/__init__.py
orientationpy/_version.py
orientationpy/analyse.py
orientationpy/generate.py
orientationpy/main.py
orientationpy/plotting.py
orientationpy-0.3.1.dist-info/licenses/AUTHORS.rst
orientationpy-0.3.1.dist-info/licenses/LICENSE.md
orientationpy-0.3.1.dist-info/METADATA
orientationpy-0.3.1.dist-info/WHEEL
orientationpy-0.3.1.dist-info/top_level.txt
orientationpy-0.3.1.dist-info/RECORD
