Metadata-Version: 2.4
Name: orientationpy
Version: 0.3.1
Summary: Package for greyscale orientation analysis on 2D and 3D images
Author-email: Edward Andò <edward.ando@epfl.ch>, Florian Aymanns <florian.aymanns@epfl.ch>, Daniel Sage <daniel.sage@epfl.ch>, Mallory Wittwer <mallory.wittwer@epfl.ch>, Alexandru Vasile <vasilealexandrupetru@gmail.com>
Maintainer-email: Edward Andò <edward.ando@epfl.ch>, Florian Aymanns <florian.aymanns@epfl.ch>
License: GPLv3
Project-URL: homepage, https://epfl-center-for-imaging.gitlab.io/orientationpy/index.html
Project-URL: documentation, https://readthedocs.org
Project-URL: repository, https://gitlab.com/epfl-center-for-imaging/orientationpy
Keywords: orientation,structure tensor,greylevel,image analysis
Classifier: Development Status :: 2 - Pre-Alpha
Classifier: Intended Audience :: Developers
Classifier: License :: OSI Approved :: GNU General Public License v3 (GPLv3)
Classifier: Natural Language :: English
Classifier: Programming Language :: Python :: 3 :: Only
Classifier: Programming Language :: Python :: 3
Classifier: Programming Language :: Python :: 3.7
Classifier: Programming Language :: Python :: 3.8
Classifier: Programming Language :: Python :: 3.9
Classifier: Programming Language :: Python :: 3.10
Classifier: Programming Language :: Python :: 3.11
Classifier: Programming Language :: Python :: 3.12
Classifier: Programming Language :: Python :: 3.13
Requires-Python: >=3.7
License-File: LICENSE.md
License-File: AUTHORS.rst
Requires-Dist: matplotlib>=3.1.3
Requires-Dist: scipy
Requires-Dist: numpy
Requires-Dist: numba>=0.57.1
Requires-Dist: numba_progress
Provides-Extra: test
Requires-Dist: pytest; extra == "test"
Requires-Dist: pytest-cov[all]; extra == "test"
Requires-Dist: tox; extra == "test"
Provides-Extra: examples
Requires-Dist: tifffile; extra == "examples"
Requires-Dist: pyvista[jupyter]; extra == "examples"
Requires-Dist: scikit-image; extra == "examples"
Provides-Extra: docs
Requires-Dist: orientationpy[examples]; extra == "docs"
Requires-Dist: sphinx; extra == "docs"
Requires-Dist: sphinx_rtd_theme; extra == "docs"
Requires-Dist: sphinx-gallery; extra == "docs"
Requires-Dist: sphinx_design; extra == "docs"
Provides-Extra: dev
Requires-Dist: orientationpy[test]; extra == "dev"
Requires-Dist: orientationpy[examples]; extra == "dev"
Requires-Dist: pip-tools; extra == "dev"
Requires-Dist: twine; extra == "dev"
Requires-Dist: pre-commit; extra == "dev"
Requires-Dist: wheel>=0.22; extra == "dev"
Requires-Dist: setuptools_scm; extra == "dev"
Dynamic: license-file
